LICENSE.md
MANIFEST.in
README.md
setup.py
mydf/__init__.py
mydf/base.py
mydf/group.py
mydf/join.py
mydf/other.py
mydf/reshape.py
mydf/select.py
mydf/set_ops.py
mydf/subset.py
mydf/summarize.py
mydf/summary_functions.py
mydf/transform.py
mydf/vector.py
mydf/window_functions.py
mydf.egg-info/PKG-INFO
mydf.egg-info/SOURCES.txt
mydf.egg-info/dependency_links.txt
mydf.egg-info/requires.txt
mydf.egg-info/top_level.txt