Metadata-Version: 1.0
Name: mydf
Version: 0.0.14
Summary: An improved version for dfply.
Home-page: https://github.com/jimmybow/mydf
Author: Jimmybow
Author-email: jimmybow@hotmail.com.tw
License: GNU General Public License v3.0
Keywords: pandas dplyr dfply
Platform: UNKNOWN
